pg_to_evalscript/__init__.py
pg_to_evalscript/conversion.py
pg_to_evalscript/evalscript.py
pg_to_evalscript/node.py
pg_to_evalscript/process_graph_utils.py
pg_to_evalscript/utils.py
pg_to_evalscript/javascript_common/common.js
pg_to_evalscript/javascript_datacube/DataCube.js
pg_to_evalscript/javascript_datacube/ndarray.js
pg_to_evalscript/javascript_processes/absolute.js
pg_to_evalscript/javascript_processes/add.js
pg_to_evalscript/javascript_processes/add_dimension.js
pg_to_evalscript/javascript_processes/aggregate_temporal.js
pg_to_evalscript/javascript_processes/aggregate_temporal_period.js
pg_to_evalscript/javascript_processes/all.js
pg_to_evalscript/javascript_processes/and.js
pg_to_evalscript/javascript_processes/any.js
pg_to_evalscript/javascript_processes/apply.js
pg_to_evalscript/javascript_processes/apply_dimension.js
pg_to_evalscript/javascript_processes/arccos.js
pg_to_evalscript/javascript_processes/arcosh.js
pg_to_evalscript/javascript_processes/arcsin.js
pg_to_evalscript/javascript_processes/arctan.js
pg_to_evalscript/javascript_processes/arctan2.js
pg_to_evalscript/javascript_processes/array_append.js
pg_to_evalscript/javascript_processes/array_apply.js
pg_to_evalscript/javascript_processes/array_concat.js
pg_to_evalscript/javascript_processes/array_contains.js
pg_to_evalscript/javascript_processes/array_create.js
pg_to_evalscript/javascript_processes/array_element.js
pg_to_evalscript/javascript_processes/array_filter.js
pg_to_evalscript/javascript_processes/array_find.js
pg_to_evalscript/javascript_processes/array_interpolate_linear.js
pg_to_evalscript/javascript_processes/array_labels.js
pg_to_evalscript/javascript_processes/arsinh.js
pg_to_evalscript/javascript_processes/artanh.js
pg_to_evalscript/javascript_processes/between.js
pg_to_evalscript/javascript_processes/ceil.js
pg_to_evalscript/javascript_processes/clip.js
pg_to_evalscript/javascript_processes/constant.js
pg_to_evalscript/javascript_processes/cos.js
pg_to_evalscript-0.2.9.dist-info/LICENSE
pg_to_evalscript-0.2.9.dist-info/METADATA
pg_to_evalscript-0.2.9.dist-info/WHEEL
pg_to_evalscript-0.2.9.dist-info/top_level.txt
pg_to_evalscript-0.2.9.dist-info/RECORD
