Metadata-Version: 2.1
Name: pg-to-evalscript
Version: 0.2.9
License-File: LICENSE
